prisoners_dilemma_sdk/__init__.py
prisoners_dilemma_sdk/core.py
prisoners_dilemma_sdk-0.0.7.dist-info/METADATA
prisoners_dilemma_sdk-0.0.7.dist-info/WHEEL
prisoners_dilemma_sdk-0.0.7.dist-info/top_level.txt
prisoners_dilemma_sdk-0.0.7.dist-info/RECORD
