Metadata-Version: 2.1
Name: prisoners-dilemma-sdk
Version: 0.0.7
Home-page: https://github.com/youssef-attai/prisoners-dilemma-sdk
Author: Youssef Atta'i
Author-email: youssefjattai@gmail.com
License: MIT
Project-URL: Source Code, https://github.com/youssef-attai/prisoners-dilemma-sdk
Classifier: Environment :: Console
Classifier: Intended Audience :: Developers
Classifier: Programming Language :: Python :: 3.10
Requires-Python: >=3.8
